T4SEfinder/__init__.py
T4SEfinder/dataset.py
T4SEfinder/model.py
T4SEfinder/prediction.py
T4SEfinder/utils.py
T4SEfinder-0.1.0.dist-info/LICENSE
T4SEfinder-0.1.0.dist-info/METADATA
T4SEfinder-0.1.0.dist-info/WHEEL
T4SEfinder-0.1.0.dist-info/top_level.txt
T4SEfinder-0.1.0.dist-info/RECORD
