Metadata-Version: 2.1
Name: T4SEfinder
Version: 0.1.0
Summary: A bioinformatics tool for genome-scale prediction of bacterial type IV secreted effectors using pre-trained protein language model.
Home-page: https://github.com/zhangyumeng1sjtu/T4SEfinder
Author: Yumeng Zhang
Author-email: zhangyumeng1@sjtu.edu.cn
License: UNKNOWN
Platform: UNKNOWN
Classifier: Programming Language :: Python :: 3
Classifier: License :: OSI Approved :: BSD License
Classifier: Operating System :: OS Independent
License-File: LICENSE
Requires-Dist: torch (==1.7.0)
Requires-Dist: pandas (==1.2.0)
Requires-Dist: numpy (==1.20.2)
Requires-Dist: joblib (==0.17.0)
Requires-Dist: biopython (==1.79)
Requires-Dist: scikit-learn (==0.24.2)
Requires-Dist: tape-proteins
